mipsolver/__init__.py
mipsolver/_solver.cpython-312-darwin.so
mipsolver/backend.py
mipsolver/constants.py
mipsolver/exceptions.py
mipsolver/expressions.py
mipsolver/model.py
mipsolver/py.typed
mipsolver-1.0.10.dist-info/METADATA
mipsolver-1.0.10.dist-info/WHEEL
mipsolver-1.0.10.dist-info/top_level.txt
mipsolver-1.0.10.dist-info/RECORD
