Metadata-Version: 2.4
Name: mipsolver
Version: 1.0.10
Summary: 高性能混合整数规划求解器，现代Python API
Author: lytreallynb
Project-URL: Homepage, https://github.com/lytreallynb/MIPSolver
Project-URL: Repository, https://github.com/lytreallynb/MIPSolver.git
Project-URL: Documentation, https://github.com/lytreallynb/MIPSolver#readme
Project-URL: Bug Tracker, https://github.com/lytreallynb/MIPSolver/issues
Keywords: optimization,linear-programming,integer-programming,mip,solver
Classifier: Development Status :: 4 - Beta
Classifier: Intended Audience :: Science/Research
Classifier: Intended Audience :: Developers
Classifier: Programming Language :: Python :: 3
Classifier: Programming Language :: Python :: 3.8
Classifier: Programming Language :: Python :: 3.9
Classifier: Programming Language :: Python :: 3.10
Classifier: Programming Language :: Python :: 3.11
Classifier: Programming Language :: Python :: 3.12
Classifier: Programming Language :: C++
Classifier: Topic :: Scientific/Engineering :: Mathematics
Classifier: Topic :: Software Development :: Libraries :: Python Modules
Requires-Python: >=3.8
